demetric/__init__.py
demetric/__init__.pyi
demetric/agg.py
demetric/metrics.py
demetric-0.1.13.dist-info/METADATA
demetric-0.1.13.dist-info/WHEEL
demetric-0.1.13.dist-info/top_level.txt
demetric-0.1.13.dist-info/RECORD
