Metadata-Version: 2.1
Name: demetric
Version: 0.1.13
Summary: Simple and composable metric tracking and logging for ML
Author-email: Marcel Claramunt <marcel@moveread.com>
Project-URL: repo, https://github.com/moveread/REPO.git
Requires-Python: >=3.10
Requires-Dist: pandas
Requires-Dist: lazy-loader
Requires-Dist: matplotlib
